
{
	"description": "Forward rate agreement bought for time period starting in 6 months and ending in 12 months. The rate is the rate which is locked in, the underlying_price is the current reference rate.",
	"data": {
		"derivative": [
			{
				"id": "6x12-fra",
				"date": "2019-01-01T00:00:00",
				"mtm_dirty": -10,
				"asset_class": "ir",
				"type": "fra",
				"position": "short",
				"currency_code": "USD",
				"notional_amount": 100,
				"rate": 1.5,
				"underlying_index": "EURIBOR",
				"underlying_index_tenor": "3m",
				"start_date": "2019-06-01T00:00:00",
				"end_date": "2020-01-01T00:00:00",
				"settlement_type": "cash",
				"underlying_price": 1.4
			}
		]
	}
}